Metadata-Version: 2.1
Name: galai
Version: 1.1.2
Summary: API for the GALACTICA model
Home-page: https://github.com/paperswithcode/galai
Author: Papers with Code
License: Apache License 2.0
Keywords: Scientific Intelligence
Classifier: Intended Audience :: Developers
Classifier: Intended Audience :: Education
Classifier: Intended Audience :: Science/Research
Classifier: License :: OSI Approved :: MIT License
Classifier: Operating System :: OS Independent
Classifier: Topic :: Scientific/Engineering :: Artificial Intelligence
Classifier: Programming Language :: Python
Classifier: Programming Language :: Python :: 3
Classifier: Programming Language :: Python :: 3.7
Classifier: Programming Language :: Python :: 3.8
Classifier: Programming Language :: Python :: 3.9
Requires-Python: >=3.7.0
License-File: LICENSE
License-File: LICENSE-MODEL.md
